{
  "id": "1503230",
  "name": "gjw",
  "font_family": "iconfont",
  "css_prefix_text": "icon",
  "description": "",
  "glyphs": [
    {
      "icon_id": "599957",
      "name": "我的",
      "font_class": "wode",
      "unicode": "e66e",
      "unicode_decimal": 58990
    },
    {
      "icon_id": "689262",
      "name": "类目 品类 分类 类别",
      "font_class": "leimupinleifenleileibie",
      "unicode": "e7f9",
      "unicode_decimal": 59385
    },
    {
      "icon_id": "1002521",
      "name": "首页",
      "font_class": "shouye",
      "unicode": "e626",
      "unicode_decimal": 58918
    },
    {
      "icon_id": "1800706",
      "name": "放大镜",
      "font_class": "magnifier",
      "unicode": "e64d",
      "unicode_decimal": 58957
    },
    {
      "icon_id": "3705938",
      "name": "红包",
      "font_class": "hongbao",
      "unicode": "e600",
      "unicode_decimal": 58880
    },
    {
      "icon_id": "5381992",
      "name": "购物车",
      "font_class": "gouwuche",
      "unicode": "e6f2",
      "unicode_decimal": 59122
    },
    {
      "icon_id": "5609639",
      "name": "表",
      "font_class": "biao",
      "unicode": "e608",
      "unicode_decimal": 58888
    },
    {
      "icon_id": "10809885",
      "name": "向右 箭头",
      "font_class": "changyongtubiao-xianxingdaochu-zhuanqu-",
      "unicode": "e74b",
      "unicode_decimal": 59211
    }
  ]
}
